yaqd_system_monitor/VERSION
yaqd_system_monitor/__init__.py
yaqd_system_monitor/__version__.py
yaqd_system_monitor/_system_monitor.py
yaqd_system_monitor/system-monitor.avpr
yaqd_system_monitor/system-monitor.toml
yaqd_system_monitor-2021.3.0.dist-info/entry_points.txt
yaqd_system_monitor-2021.3.0.dist-info/LICENSE
yaqd_system_monitor-2021.3.0.dist-info/WHEEL
yaqd_system_monitor-2021.3.0.dist-info/METADATA
yaqd_system_monitor-2021.3.0.dist-info/RECORD
