Metadata-Version: 2.1
Name: yaqd-system-monitor
Version: 2021.3.0
Summary: yaq daemon for monitoring system usage
Home-page: https://yaq.fyi
License: UNKNOWN
Author: yaq developers
Author-email: blaise@untzag.com
Requires-Python: >=3.7
Classifier: Development Status :: 2 - Pre-Alpha
Classifier: Intended Audience :: Science/Research
Classifier: License :: OSI Approved :: GNU Lesser General Public License v3 (LGPLv3)
Classifier: Natural Language :: English
Classifier: Programming Language :: Python :: 3
Classifier: Programming Language :: Python :: 3.7
Classifier: Programming Language :: Python :: 3.8
Classifier: Topic :: Scientific/Engineering
Requires-Dist: yaqd-core>=2021.3.0
Requires-Dist: psutil
Requires-Dist: uptime
Requires-Dist: black ; extra == "dev"
Requires-Dist: pre-commit ; extra == "dev"
Requires-Dist: mypy ; extra == "dev"
Project-URL: Documentation, https://control.yaq.fyi/
Project-URL: Issues, https://gitlab.com/yaq/yaqd-control/-/issues
Project-URL: Source, https://gitlab.com/yaq/yaqd-control
Provides-Extra: dev
